LICENSE.txt
README.md
pyproject.toml
requirements.txt
uroman/__init__.py
uroman/__main__.py
uroman/uroman.py
uroman/data/Chinese_to_Pinyin.txt
uroman/data/ISO-639-3-list.txt
uroman/data/NumProps.jsonl
uroman/data/Scripts.txt
uroman/data/UnicodeData.txt
uroman/data/UnicodeDataOverwrite.txt
uroman/data/UnicodeDataProps.txt
uroman/data/UnicodeDataPropsCJK.txt
uroman/data/UnicodeDataPropsHangul.txt
uroman/data/language-properties.txt
uroman/data/romanization-auto-table.txt
uroman/data/romanization-table-arabic-block.txt
uroman/data/romanization-table.txt
uroman/mini-test/fas.txt
uroman/mini-test/hin.txt
uroman/mini-test/line_with_non_utf8.txt
uroman/mini-test/multi-script.txt
uroman/mini-test/multi-script.uroman-ref.txt
uroman-1.3.1.1.dist-info/METADATA
uroman-1.3.1.1.dist-info/WHEEL
uroman-1.3.1.1.dist-info/entry_points.txt
uroman-1.3.1.1.dist-info/licenses/LICENSE.txt
uroman-1.3.1.1.dist-info/RECORD
