Metadata-Version: 2.3
Name: uroman
Version: 1.3.1.1
Summary: uroman is a universal romanizer. It converts text in any script to the standard Latin alphabet.
Project-URL: Homepage, https://github.com/isi-nlp/uroman
Project-URL: Repository, https://github.com/isi-nlp/uroman
Project-URL: Bug Tracker, https://github.com/isi-nlp/uroman/issues
Author-email: Ulf Hermjakob <ulf@isi.edu>
Maintainer-email: Ulf Hermjakob <ulf@isi.edu>
License: Copyright (C) 2015-2020 Ulf Hermjakob, USC Information Sciences Institute
License-File: LICENSE.txt
Keywords: NLP,computational linguistics,machine translation,natural language processing,romanization,string similarity
Classifier: Development Status :: 4 - Beta
Classifier: Intended Audience :: Developers
Classifier: License :: OSI Approved :: Apache Software License
Classifier: Programming Language :: Python :: 3 :: Only
Classifier: Topic :: Text Processing
Classifier: Topic :: Text Processing :: General
Classifier: Topic :: Text Processing :: Linguistic
Classifier: Topic :: Utilities
Requires-Python: >=3.10
Requires-Dist: regex>=2024.5.15
